{
  "state": "California",
  "fips": "06",
  "credits": [
    {
      "label": "Redistricting Data Hub",
      "url": "https://redistrictingdatahub.org",
      "note": "precinct election results & shapefiles"
    },
    {
      "label": "NHGIS",
      "url": "https://www.nhgis.org",
      "note": "congressional district boundaries"
    },
    {
      "label": "MIT Election Lab",
      "url": "https://electionlab.mit.edu/data",
      "note": "US House election returns 1976\u20132024"
    },
    {
      "label": "US Census TIGER",
      "url": "https://www.census.gov/geographies/mapping-files/time-series/geo/tiger-line-file.html",
      "note": "base geography"
    }
  ],
  "cycles": [
    {
      "cycle_year": 1992,
      "congress": 103,
      "total_seats": 52,
      "redistricting_controller": "Democrat",
      "notes": "Governor Pete Wilson (R) vetoed the Democratic legislature's maps; a special master drew initial maps, then a ballot initiative (Prop 118/119) failed; the CA Supreme Court appointed masters who drew the maps used through the cycle. California gained 7 seats from the 1990 census.",
      "efficiency_gap": 0.0649,
      "mean_median_diff": 0.0322,
      "seats_d": 30,
      "seats_r": 22,
      "votes_d": 5446965,
      "votes_r": 4365155,
      "seat_vote_ratio_d": 1.0393,
      "avg_compactness": 0.2442,
      "competitiveness": {
        "solid_d": 22,
        "lean_d": 3,
        "competitive": 10,
        "lean_r": 7,
        "solid_r": 10
      },
      "districts": [
        {
          "district": 1,
          "won_by": "D",
          "partisan_lean_d": 0.5138,
          "polsby_popper": 0.1195,
          "d_votes": 119676,
          "r_votes": 113266,
          "total_votes_cast": 251206,
          "margin_pct": 0.0275,
          "contested": true
        },
        {
          "district": 2,
          "won_by": "R",
          "partisan_lean_d": 0.3003,
          "polsby_popper": 0.326,
          "d_votes": 71780,
          "r_votes": 167247,
          "total_votes_cast": 256556,
          "margin_pct": 0.3994,
          "contested": true
        },
        {
          "district": 3,
          "won_by": "D",
          "partisan_lean_d": 0.5597,
          "polsby_popper": 0.1807,
          "d_votes": 122149,
          "r_votes": 96092,
          "total_votes_cast": 238685,
          "margin_pct": 0.1194,
          "contested": true
        },
        {
          "district": 4,
          "won_by": "R",
          "partisan_lean_d": 0.4784,
          "polsby_popper": 0.3549,
          "d_votes": 129489,
          "r_votes": 141155,
          "total_votes_cast": 283365,
          "margin_pct": 0.0431,
          "contested": true
        },
        {
          "district": 5,
          "won_by": "D",
          "partisan_lean_d": 0.7294,
          "polsby_popper": 0.3428,
          "d_votes": 158250,
          "r_votes": 58698,
          "total_votes_cast": 230560,
          "margin_pct": 0.4589,
          "contested": true
        },
        {
          "district": 6,
          "won_by": "D",
          "partisan_lean_d": 0.6597,
          "polsby_popper": 0.1123,
          "d_votes": 190322,
          "r_votes": 98171,
          "total_votes_cast": 291786,
          "margin_pct": 0.3194,
          "contested": true
        },
        {
          "district": 7,
          "won_by": "D",
          "partisan_lean_d": 0.7366,
          "polsby_popper": 0.0412,
          "d_votes": 153320,
          "r_votes": 54822,
          "total_votes_cast": 217982,
          "margin_pct": 0.4732,
          "contested": true
        },
        {
          "district": 8,
          "won_by": "D",
          "partisan_lean_d": 0.8819,
          "polsby_popper": 0.0916,
          "d_votes": 191906,
          "r_votes": 25693,
          "total_votes_cast": 232691,
          "margin_pct": 0.7639,
          "contested": true
        },
        {
          "district": 9,
          "won_by": "D",
          "partisan_lean_d": 0.7536,
          "polsby_popper": 0.1267,
          "d_votes": 164265,
          "r_votes": 53707,
          "total_votes_cast": 228467,
          "margin_pct": 0.5072,
          "contested": true
        },
        {
          "district": 10,
          "won_by": "R",
          "partisan_lean_d": 0.4803,
          "polsby_popper": 0.2389,
          "d_votes": 134635,
          "r_votes": 145702,
          "total_votes_cast": 280429,
          "margin_pct": 0.0395,
          "contested": true
        },
        {
          "district": 11,
          "won_by": "R",
          "partisan_lean_d": 0.4894,
          "polsby_popper": 0.2265,
          "d_votes": 90539,
          "r_votes": 94453,
          "total_votes_cast": 198490,
          "margin_pct": 0.0212,
          "contested": true
        },
        {
          "district": 12,
          "won_by": "D",
          "partisan_lean_d": 0.7469,
          "polsby_popper": 0.0924,
          "d_votes": 157205,
          "r_votes": 53278,
          "total_votes_cast": 228407,
          "margin_pct": 0.4938,
          "contested": true
        },
        {
          "district": 13,
          "won_by": "D",
          "partisan_lean_d": 0.6559,
          "polsby_popper": 0.1688,
          "d_votes": 123795,
          "r_votes": 64953,
          "total_votes_cast": 205516,
          "margin_pct": 0.3117,
          "contested": true
        },
        {
          "district": 14,
          "won_by": "D",
          "partisan_lean_d": 0.5921,
          "polsby_popper": 0.2228,
          "d_votes": 146873,
          "r_votes": 101202,
          "total_votes_cast": 259222,
          "margin_pct": 0.1841,
          "contested": true
        },
        {
          "district": 15,
          "won_by": "D",
          "partisan_lean_d": 0.6705,
          "polsby_popper": 0.2016,
          "d_votes": 168617,
          "r_votes": 82875,
          "total_votes_cast": 265370,
          "margin_pct": 0.3409,
          "contested": true
        },
        {
          "district": 16,
          "won_by": "D",
          "partisan_lean_d": 0.6598,
          "polsby_popper": 0.2798,
          "d_votes": 96661,
          "r_votes": 49843,
          "total_votes_cast": 155883,
          "margin_pct": 0.3196,
          "contested": true
        },
        {
          "district": 17,
          "won_by": "D",
          "partisan_lean_d": 0.7521,
          "polsby_popper": 0.3095,
          "d_votes": 151565,
          "r_votes": 49947,
          "total_votes_cast": 210367,
          "margin_pct": 0.5043,
          "contested": true
        },
        {
          "district": 18,
          "won_by": "D",
          "partisan_lean_d": 1.0,
          "polsby_popper": 0.323,
          "d_votes": 139704,
          "r_votes": 0,
          "total_votes_cast": 165011,
          "margin_pct": null,
          "contested": false
        },
        {
          "district": 19,
          "won_by": "D",
          "partisan_lean_d": 0.5025,
          "polsby_popper": 0.2693,
          "d_votes": 101619,
          "r_votes": 100590,
          "total_votes_cast": 216640,
          "margin_pct": 0.0051,
          "contested": true
        },
        {
          "district": 20,
          "won_by": "D",
          "partisan_lean_d": 0.6485,
          "polsby_popper": 0.2089,
          "d_votes": 72679,
          "r_votes": 39388,
          "total_votes_cast": 112067,
          "margin_pct": 0.2971,
          "contested": true
        },
        {
          "district": 21,
          "won_by": "R",
          "partisan_lean_d": 0.3476,
          "polsby_popper": 0.1952,
          "d_votes": 68058,
          "r_votes": 127758,
          "total_votes_cast": 195965,
          "margin_pct": 0.3049,
          "contested": true
        },
        {
          "district": 22,
          "won_by": "R",
          "partisan_lean_d": 0.3995,
          "polsby_popper": 0.2118,
          "d_votes": 87328,
          "r_votes": 131242,
          "total_votes_cast": 249926,
          "margin_pct": 0.2009,
          "contested": true
        },
        {
          "district": 23,
          "won_by": "R",
          "partisan_lean_d": 0.4331,
          "polsby_popper": 0.3015,
          "d_votes": 88225,
          "r_votes": 115504,
          "total_votes_cast": 212881,
          "margin_pct": 0.1339,
          "contested": true
        },
        {
          "district": 24,
          "won_by": "D",
          "partisan_lean_d": 0.5867,
          "polsby_popper": 0.2355,
          "d_votes": 141742,
          "r_votes": 99835,
          "total_votes_cast": 255267,
          "margin_pct": 0.1735,
          "contested": true
        },
        {
          "district": 25,
          "won_by": "R",
          "partisan_lean_d": 0.3887,
          "polsby_popper": 0.4068,
          "d_votes": 72233,
          "r_votes": 113611,
          "total_votes_cast": 218715,
          "margin_pct": 0.2226,
          "contested": true
        },
        {
          "district": 26,
          "won_by": "D",
          "partisan_lean_d": 0.6694,
          "polsby_popper": 0.3259,
          "d_votes": 73807,
          "r_votes": 36453,
          "total_votes_cast": 120908,
          "margin_pct": 0.3388,
          "contested": true
        },
        {
          "district": 27,
          "won_by": "R",
          "partisan_lean_d": 0.4426,
          "polsby_popper": 0.1658,
          "d_votes": 83805,
          "r_votes": 105521,
          "total_votes_cast": 212450,
          "margin_pct": 0.1147,
          "contested": true
        },
        {
          "district": 28,
          "won_by": "R",
          "partisan_lean_d": 0.3848,
          "polsby_popper": 0.1873,
          "d_votes": 76525,
          "r_votes": 122353,
          "total_votes_cast": 209382,
          "margin_pct": 0.2304,
          "contested": true
        },
        {
          "district": 29,
          "won_by": "D",
          "partisan_lean_d": 0.7048,
          "polsby_popper": 0.2986,
          "d_votes": 160312,
          "r_votes": 67141,
          "total_votes_cast": 261486,
          "margin_pct": 0.4096,
          "contested": true
        },
        {
          "district": 30,
          "won_by": "D",
          "partisan_lean_d": 0.709,
          "polsby_popper": 0.198,
          "d_votes": 48800,
          "r_votes": 20034,
          "total_votes_cast": 83543,
          "margin_pct": 0.4179,
          "contested": true
        },
        {
          "district": 31,
          "won_by": "D",
          "partisan_lean_d": 0.6257,
          "polsby_popper": 0.217,
          "d_votes": 68324,
          "r_votes": 40873,
          "total_votes_cast": 109197,
          "margin_pct": 0.2514,
          "contested": true
        },
        {
          "district": 32,
          "won_by": "D",
          "partisan_lean_d": 1.0,
          "polsby_popper": 0.4213,
          "d_votes": 150644,
          "r_votes": 0,
          "total_votes_cast": 172812,
          "margin_pct": null,
          "contested": false
        },
        {
          "district": 33,
          "won_by": "D",
          "partisan_lean_d": 0.6748,
          "polsby_popper": 0.2553,
          "d_votes": 32010,
          "r_votes": 15428,
          "total_votes_cast": 50779,
          "margin_pct": 0.3496,
          "contested": true
        },
        {
          "district": 34,
          "won_by": "D",
          "partisan_lean_d": 0.6431,
          "polsby_popper": 0.2312,
          "d_votes": 91738,
          "r_votes": 50907,
          "total_votes_cast": 149718,
          "margin_pct": 0.2862,
          "contested": true
        },
        {
          "district": 35,
          "won_by": "D",
          "partisan_lean_d": 0.8553,
          "polsby_popper": 0.2305,
          "d_votes": 102941,
          "r_votes": 17417,
          "total_votes_cast": 124776,
          "margin_pct": 0.7106,
          "contested": true
        },
        {
          "district": 36,
          "won_by": "D",
          "partisan_lean_d": 0.5341,
          "polsby_popper": 0.0637,
          "d_votes": 125751,
          "r_votes": 109684,
          "total_votes_cast": 351397,
          "margin_pct": 0.0682,
          "contested": true
        },
        {
          "district": 37,
          "won_by": "D",
          "partisan_lean_d": 1.0,
          "polsby_popper": 0.2946,
          "d_votes": 97159,
          "r_votes": 0,
          "total_votes_cast": 113337,
          "margin_pct": null,
          "contested": false
        },
        {
          "district": 38,
          "won_by": "R",
          "partisan_lean_d": 0.4715,
          "polsby_popper": 0.1022,
          "d_votes": 82108,
          "r_votes": 92038,
          "total_votes_cast": 189321,
          "margin_pct": 0.057,
          "contested": true
        },
        {
          "district": 39,
          "won_by": "R",
          "partisan_lean_d": 0.4002,
          "polsby_popper": 0.2696,
          "d_votes": 81728,
          "r_votes": 122472,
          "total_votes_cast": 213684,
          "margin_pct": 0.1995,
          "contested": true
        },
        {
          "district": 40,
          "won_by": "R",
          "partisan_lean_d": 0.3302,
          "polsby_popper": 0.4394,
          "d_votes": 63881,
          "r_votes": 129563,
          "total_votes_cast": 205283,
          "margin_pct": 0.3395,
          "contested": true
        },
        {
          "district": 41,
          "won_by": "R",
          "partisan_lean_d": 0.3661,
          "polsby_popper": 0.3285,
          "d_votes": 58777,
          "r_votes": 101753,
          "total_votes_cast": 170666,
          "margin_pct": 0.2677,
          "contested": true
        },
        {
          "district": 42,
          "won_by": "D",
          "partisan_lean_d": 0.5353,
          "polsby_popper": 0.3653,
          "d_votes": 79780,
          "r_votes": 69251,
          "total_votes_cast": 157455,
          "margin_pct": 0.0706,
          "contested": true
        },
        {
          "district": 43,
          "won_by": "R",
          "partisan_lean_d": 0.4985,
          "polsby_popper": 0.2815,
          "d_votes": 88468,
          "r_votes": 88987,
          "total_votes_cast": 190639,
          "margin_pct": 0.0029,
          "contested": true
        },
        {
          "district": 44,
          "won_by": "R",
          "partisan_lean_d": 0.4254,
          "polsby_popper": 0.3698,
          "d_votes": 81693,
          "r_votes": 110333,
          "total_votes_cast": 203541,
          "margin_pct": 0.1491,
          "contested": true
        },
        {
          "district": 45,
          "won_by": "R",
          "partisan_lean_d": 0.417,
          "polsby_popper": 0.1855,
          "d_votes": 88508,
          "r_votes": 123731,
          "total_votes_cast": 227016,
          "margin_pct": 0.166,
          "contested": true
        },
        {
          "district": 46,
          "won_by": "R",
          "partisan_lean_d": 0.4494,
          "polsby_popper": 0.3489,
          "d_votes": 45435,
          "r_votes": 55659,
          "total_votes_cast": 110806,
          "margin_pct": 0.1011,
          "contested": true
        },
        {
          "district": 47,
          "won_by": "R",
          "partisan_lean_d": 0.318,
          "polsby_popper": 0.3431,
          "d_votes": 76924,
          "r_votes": 165004,
          "total_votes_cast": 254257,
          "margin_pct": 0.3641,
          "contested": true
        },
        {
          "district": 48,
          "won_by": "R",
          "partisan_lean_d": 0.3236,
          "polsby_popper": 0.1996,
          "d_votes": 67415,
          "r_votes": 140935,
          "total_votes_cast": 230495,
          "margin_pct": 0.3529,
          "contested": true
        },
        {
          "district": 49,
          "won_by": "D",
          "partisan_lean_d": 0.5452,
          "polsby_popper": 0.0738,
          "d_votes": 127280,
          "r_votes": 106170,
          "total_votes_cast": 248898,
          "margin_pct": 0.0904,
          "contested": true
        },
        {
          "district": 50,
          "won_by": "D",
          "partisan_lean_d": 0.6616,
          "polsby_popper": 0.2627,
          "d_votes": 77293,
          "r_votes": 39531,
          "total_votes_cast": 136626,
          "margin_pct": 0.3232,
          "contested": true
        },
        {
          "district": 51,
          "won_by": "R",
          "partisan_lean_d": 0.375,
          "polsby_popper": 0.3305,
          "d_votes": 85148,
          "r_votes": 141890,
          "total_votes_cast": 252995,
          "margin_pct": 0.2499,
          "contested": true
        },
        {
          "district": 52,
          "won_by": "R",
          "partisan_lean_d": 0.438,
          "polsby_popper": 0.3183,
          "d_votes": 88076,
          "r_votes": 112995,
          "total_votes_cast": 213784,
          "margin_pct": 0.1239,
          "contested": true
        }
      ]
    },
    {
      "cycle_year": 2002,
      "congress": 108,
      "total_seats": 53,
      "redistricting_controller": "Democrat",
      "notes": "Governor Gray Davis (D) and a Democratic legislature drew an incumbent-protection gerrymander so effective it produced zero seat changes in 2002 and 2004; California gained 1 seat from the 2000 census. The maps were widely criticized as the 'incumbent protection act of 2001.'",
      "efficiency_gap": 0.0109,
      "mean_median_diff": -0.0785,
      "seats_d": 33,
      "seats_r": 20,
      "votes_d": 3731081,
      "votes_r": 3225666,
      "seat_vote_ratio_d": 1.1609,
      "avg_compactness": 0.1532,
      "competitiveness": {
        "solid_d": 30,
        "lean_d": 2,
        "competitive": 1,
        "lean_r": 0,
        "solid_r": 20
      },
      "districts": [
        {
          "district": 1,
          "won_by": "D",
          "partisan_lean_d": 0.6641,
          "polsby_popper": 0.1011,
          "d_votes": 118669,
          "r_votes": 60013,
          "total_votes_cast": 185216,
          "margin_pct": 0.3283,
          "contested": true
        },
        {
          "district": 2,
          "won_by": "R",
          "partisan_lean_d": 0.3082,
          "polsby_popper": 0.3011,
          "d_votes": 52455,
          "r_votes": 117747,
          "total_votes_cast": 178985,
          "margin_pct": 0.3836,
          "contested": true
        },
        {
          "district": 3,
          "won_by": "R",
          "partisan_lean_d": 0.3555,
          "polsby_popper": 0.1042,
          "d_votes": 67136,
          "r_votes": 121732,
          "total_votes_cast": 194918,
          "margin_pct": 0.2891,
          "contested": true
        },
        {
          "district": 4,
          "won_by": "R",
          "partisan_lean_d": 0.3299,
          "polsby_popper": 0.3056,
          "d_votes": 72860,
          "r_votes": 147997,
          "total_votes_cast": 228506,
          "margin_pct": 0.3402,
          "contested": true
        },
        {
          "district": 5,
          "won_by": "D",
          "partisan_lean_d": 0.7274,
          "polsby_popper": 0.1786,
          "d_votes": 92726,
          "r_votes": 34749,
          "total_votes_cast": 131578,
          "margin_pct": 0.4548,
          "contested": true
        },
        {
          "district": 6,
          "won_by": "D",
          "partisan_lean_d": 0.6925,
          "polsby_popper": 0.1162,
          "d_votes": 139750,
          "r_votes": 62052,
          "total_votes_cast": 209563,
          "margin_pct": 0.385,
          "contested": true
        },
        {
          "district": 7,
          "won_by": "D",
          "partisan_lean_d": 0.7279,
          "polsby_popper": 0.0343,
          "d_votes": 97849,
          "r_votes": 36584,
          "total_votes_cast": 138376,
          "margin_pct": 0.4557,
          "contested": true
        },
        {
          "district": 8,
          "won_by": "D",
          "partisan_lean_d": 0.8642,
          "polsby_popper": 0.0444,
          "d_votes": 127684,
          "r_votes": 20063,
          "total_votes_cast": 160441,
          "margin_pct": 0.7284,
          "contested": true
        },
        {
          "district": 9,
          "won_by": "D",
          "partisan_lean_d": 0.8429,
          "polsby_popper": 0.1275,
          "d_votes": 135893,
          "r_votes": 25333,
          "total_votes_cast": 166917,
          "margin_pct": 0.6857,
          "contested": true
        },
        {
          "district": 10,
          "won_by": "D",
          "partisan_lean_d": 1.0,
          "polsby_popper": 0.0344,
          "d_votes": 126390,
          "r_votes": 0,
          "total_votes_cast": 167197,
          "margin_pct": null,
          "contested": false
        },
        {
          "district": 11,
          "won_by": "R",
          "partisan_lean_d": 0.3969,
          "polsby_popper": 0.0834,
          "d_votes": 69035,
          "r_votes": 104921,
          "total_votes_cast": 173956,
          "margin_pct": 0.2063,
          "contested": true
        },
        {
          "district": 12,
          "won_by": "D",
          "partisan_lean_d": 0.7334,
          "polsby_popper": 0.0673,
          "d_votes": 105597,
          "r_votes": 38381,
          "total_votes_cast": 154984,
          "margin_pct": 0.4668,
          "contested": true
        },
        {
          "district": 13,
          "won_by": "D",
          "partisan_lean_d": 0.7631,
          "polsby_popper": 0.1262,
          "d_votes": 86495,
          "r_votes": 26852,
          "total_votes_cast": 121723,
          "margin_pct": 0.5262,
          "contested": true
        },
        {
          "district": 14,
          "won_by": "D",
          "partisan_lean_d": 0.7077,
          "polsby_popper": 0.0905,
          "d_votes": 117055,
          "r_votes": 48346,
          "total_votes_cast": 171678,
          "margin_pct": 0.4154,
          "contested": true
        },
        {
          "district": 15,
          "won_by": "D",
          "partisan_lean_d": 0.6796,
          "polsby_popper": 0.0522,
          "d_votes": 87482,
          "r_votes": 41251,
          "total_votes_cast": 133022,
          "margin_pct": 0.3591,
          "contested": true
        },
        {
          "district": 16,
          "won_by": "D",
          "partisan_lean_d": 0.6922,
          "polsby_popper": 0.095,
          "d_votes": 72370,
          "r_votes": 32182,
          "total_votes_cast": 107986,
          "margin_pct": 0.3844,
          "contested": true
        },
        {
          "district": 17,
          "won_by": "D",
          "partisan_lean_d": 0.7159,
          "polsby_popper": 0.2729,
          "d_votes": 101632,
          "r_votes": 40334,
          "total_votes_cast": 149296,
          "margin_pct": 0.4318,
          "contested": true
        },
        {
          "district": 18,
          "won_by": "D",
          "partisan_lean_d": 0.5417,
          "polsby_popper": 0.1401,
          "d_votes": 56181,
          "r_votes": 47528,
          "total_votes_cast": 109593,
          "margin_pct": 0.0834,
          "contested": true
        },
        {
          "district": 19,
          "won_by": "R",
          "partisan_lean_d": 0.3086,
          "polsby_popper": 0.1568,
          "d_votes": 47403,
          "r_votes": 106209,
          "total_votes_cast": 157802,
          "margin_pct": 0.3828,
          "contested": true
        },
        {
          "district": 20,
          "won_by": "D",
          "partisan_lean_d": 0.6502,
          "polsby_popper": 0.1378,
          "d_votes": 47627,
          "r_votes": 25628,
          "total_votes_cast": 74770,
          "margin_pct": 0.3003,
          "contested": true
        },
        {
          "district": 21,
          "won_by": "R",
          "partisan_lean_d": 0.2712,
          "polsby_popper": 0.3258,
          "d_votes": 32584,
          "r_votes": 87544,
          "total_votes_cast": 124198,
          "margin_pct": 0.4575,
          "contested": true
        },
        {
          "district": 22,
          "won_by": "R",
          "partisan_lean_d": 0.2445,
          "polsby_popper": 0.19,
          "d_votes": 38988,
          "r_votes": 120473,
          "total_votes_cast": 164285,
          "margin_pct": 0.511,
          "contested": true
        },
        {
          "district": 23,
          "won_by": "D",
          "partisan_lean_d": 0.6047,
          "polsby_popper": 0.0191,
          "d_votes": 95752,
          "r_votes": 62604,
          "total_votes_cast": 162222,
          "margin_pct": 0.2093,
          "contested": true
        },
        {
          "district": 24,
          "won_by": "R",
          "partisan_lean_d": 0.3276,
          "polsby_popper": 0.2219,
          "d_votes": 58755,
          "r_votes": 120585,
          "total_votes_cast": 185006,
          "margin_pct": 0.3448,
          "contested": true
        },
        {
          "district": 25,
          "won_by": "R",
          "partisan_lean_d": 0.3238,
          "polsby_popper": 0.1958,
          "d_votes": 38674,
          "r_votes": 80775,
          "total_votes_cast": 124336,
          "margin_pct": 0.3525,
          "contested": true
        },
        {
          "district": 26,
          "won_by": "R",
          "partisan_lean_d": 0.3443,
          "polsby_popper": 0.1285,
          "d_votes": 50081,
          "r_votes": 95360,
          "total_votes_cast": 149530,
          "margin_pct": 0.3113,
          "contested": true
        },
        {
          "district": 27,
          "won_by": "D",
          "partisan_lean_d": 0.6196,
          "polsby_popper": 0.119,
          "d_votes": 79815,
          "r_votes": 48996,
          "total_votes_cast": 128811,
          "margin_pct": 0.2393,
          "contested": true
        },
        {
          "district": 28,
          "won_by": "D",
          "partisan_lean_d": 0.7551,
          "polsby_popper": 0.2092,
          "d_votes": 73771,
          "r_votes": 23926,
          "total_votes_cast": 103326,
          "margin_pct": 0.5102,
          "contested": true
        },
        {
          "district": 29,
          "won_by": "D",
          "partisan_lean_d": 0.6518,
          "polsby_popper": 0.0861,
          "d_votes": 76036,
          "r_votes": 40616,
          "total_votes_cast": 121541,
          "margin_pct": 0.3036,
          "contested": true
        },
        {
          "district": 30,
          "won_by": "D",
          "partisan_lean_d": 0.7037,
          "polsby_popper": 0.2363,
          "d_votes": 130604,
          "r_votes": 54989,
          "total_votes_cast": 185593,
          "margin_pct": 0.4074,
          "contested": true
        },
        {
          "district": 31,
          "won_by": "D",
          "partisan_lean_d": 0.8115,
          "polsby_popper": 0.1127,
          "d_votes": 54569,
          "r_votes": 12674,
          "total_votes_cast": 67243,
          "margin_pct": 0.623,
          "contested": true
        },
        {
          "district": 32,
          "won_by": "D",
          "partisan_lean_d": 0.7147,
          "polsby_popper": 0.0928,
          "d_votes": 58530,
          "r_votes": 23366,
          "total_votes_cast": 85079,
          "margin_pct": 0.4294,
          "contested": true
        },
        {
          "district": 33,
          "won_by": "D",
          "partisan_lean_d": 0.8541,
          "polsby_popper": 0.1282,
          "d_votes": 97779,
          "r_votes": 16699,
          "total_votes_cast": 118449,
          "margin_pct": 0.7083,
          "contested": true
        },
        {
          "district": 34,
          "won_by": "D",
          "partisan_lean_d": 0.7404,
          "polsby_popper": 0.2193,
          "d_votes": 48734,
          "r_votes": 17090,
          "total_votes_cast": 65824,
          "margin_pct": 0.4807,
          "contested": true
        },
        {
          "district": 35,
          "won_by": "D",
          "partisan_lean_d": 0.8001,
          "polsby_popper": 0.1642,
          "d_votes": 72401,
          "r_votes": 18094,
          "total_votes_cast": 93407,
          "margin_pct": 0.6001,
          "contested": true
        },
        {
          "district": 36,
          "won_by": "D",
          "partisan_lean_d": 0.6367,
          "polsby_popper": 0.0727,
          "d_votes": 88198,
          "r_votes": 50328,
          "total_votes_cast": 143751,
          "margin_pct": 0.2734,
          "contested": true
        },
        {
          "district": 37,
          "won_by": "D",
          "partisan_lean_d": 0.7589,
          "polsby_popper": 0.1966,
          "d_votes": 63445,
          "r_votes": 20154,
          "total_votes_cast": 87012,
          "margin_pct": 0.5178,
          "contested": true
        },
        {
          "district": 38,
          "won_by": "D",
          "partisan_lean_d": 0.7302,
          "polsby_popper": 0.0715,
          "d_votes": 62600,
          "r_votes": 23126,
          "total_votes_cast": 88027,
          "margin_pct": 0.4605,
          "contested": true
        },
        {
          "district": 39,
          "won_by": "D",
          "partisan_lean_d": 0.5731,
          "polsby_popper": 0.0657,
          "d_votes": 52256,
          "r_votes": 38925,
          "total_votes_cast": 95346,
          "margin_pct": 0.1462,
          "contested": true
        },
        {
          "district": 40,
          "won_by": "R",
          "partisan_lean_d": 0.3035,
          "polsby_popper": 0.1047,
          "d_votes": 40265,
          "r_votes": 92422,
          "total_votes_cast": 136642,
          "margin_pct": 0.3931,
          "contested": true
        },
        {
          "district": 41,
          "won_by": "R",
          "partisan_lean_d": 0.3054,
          "polsby_popper": 0.4379,
          "d_votes": 40155,
          "r_votes": 91326,
          "total_votes_cast": 135533,
          "margin_pct": 0.3892,
          "contested": true
        },
        {
          "district": 42,
          "won_by": "R",
          "partisan_lean_d": 0.2994,
          "polsby_popper": 0.1539,
          "d_votes": 42090,
          "r_votes": 98476,
          "total_votes_cast": 145246,
          "margin_pct": 0.4011,
          "contested": true
        },
        {
          "district": 43,
          "won_by": "D",
          "partisan_lean_d": 0.6855,
          "polsby_popper": 0.2781,
          "d_votes": 45374,
          "r_votes": 20821,
          "total_votes_cast": 68340,
          "margin_pct": 0.3709,
          "contested": true
        },
        {
          "district": 44,
          "won_by": "R",
          "partisan_lean_d": 0.3315,
          "polsby_popper": 0.2221,
          "d_votes": 38021,
          "r_votes": 76686,
          "total_votes_cast": 120463,
          "margin_pct": 0.3371,
          "contested": true
        },
        {
          "district": 45,
          "won_by": "R",
          "partisan_lean_d": 0.3341,
          "polsby_popper": 0.269,
          "d_votes": 43692,
          "r_votes": 87101,
          "total_votes_cast": 133533,
          "margin_pct": 0.3319,
          "contested": true
        },
        {
          "district": 46,
          "won_by": "R",
          "partisan_lean_d": 0.3588,
          "polsby_popper": 0.0273,
          "d_votes": 60890,
          "r_votes": 108807,
          "total_votes_cast": 176265,
          "margin_pct": 0.2824,
          "contested": true
        },
        {
          "district": 47,
          "won_by": "D",
          "partisan_lean_d": 0.6358,
          "polsby_popper": 0.1315,
          "d_votes": 42501,
          "r_votes": 24346,
          "total_votes_cast": 70178,
          "margin_pct": 0.2716,
          "contested": true
        },
        {
          "district": 48,
          "won_by": "R",
          "partisan_lean_d": 0.2935,
          "polsby_popper": 0.1719,
          "d_votes": 51058,
          "r_votes": 122884,
          "total_votes_cast": 179549,
          "margin_pct": 0.4129,
          "contested": true
        },
        {
          "district": 49,
          "won_by": "R",
          "partisan_lean_d": 0.0,
          "polsby_popper": 0.1605,
          "d_votes": 0,
          "r_votes": 94594,
          "total_votes_cast": 122497,
          "margin_pct": null,
          "contested": false
        },
        {
          "district": 50,
          "won_by": "R",
          "partisan_lean_d": 0.3346,
          "polsby_popper": 0.2473,
          "d_votes": 55855,
          "r_votes": 111095,
          "total_votes_cast": 172701,
          "margin_pct": 0.3309,
          "contested": true
        },
        {
          "district": 51,
          "won_by": "D",
          "partisan_lean_d": 0.5956,
          "polsby_popper": 0.2387,
          "d_votes": 59541,
          "r_votes": 40430,
          "total_votes_cast": 102787,
          "margin_pct": 0.1912,
          "contested": true
        },
        {
          "district": 52,
          "won_by": "R",
          "partisan_lean_d": 0.2685,
          "polsby_popper": 0.2276,
          "d_votes": 43526,
          "r_votes": 118561,
          "total_votes_cast": 169010,
          "margin_pct": 0.4629,
          "contested": true
        },
        {
          "district": 53,
          "won_by": "D",
          "partisan_lean_d": 0.6221,
          "polsby_popper": 0.026,
          "d_votes": 72252,
          "r_votes": 43891,
          "total_votes_cast": 116180,
          "margin_pct": 0.2442,
          "contested": true
        }
      ]
    },
    {
      "cycle_year": 2012,
      "congress": 113,
      "total_seats": 53,
      "redistricting_controller": "Independent Commission (CCRC)",
      "notes": "Proposition 11 (2008) created the California Citizens Redistricting Commission; Proposition 20 (2010) extended its authority to congressional districts. The CCRC's maps were the first non-legislatively drawn congressional maps in California in decades.",
      "efficiency_gap": 0.0317,
      "mean_median_diff": -0.0113,
      "seats_d": 38,
      "seats_r": 15,
      "votes_d": 7392703,
      "votes_r": 4530012,
      "seat_vote_ratio_d": 1.1563,
      "avg_compactness": 0.1966,
      "competitiveness": {
        "solid_d": 28,
        "lean_d": 5,
        "competitive": 7,
        "lean_r": 5,
        "solid_r": 8
      },
      "districts": [
        {
          "district": 1,
          "won_by": "R",
          "partisan_lean_d": 0.4262,
          "polsby_popper": 0.2924,
          "d_votes": 125386,
          "r_votes": 168827,
          "total_votes_cast": 294213,
          "margin_pct": 0.1477,
          "contested": true
        },
        {
          "district": 2,
          "won_by": "D",
          "partisan_lean_d": 0.7124,
          "polsby_popper": 0.0981,
          "d_votes": 226216,
          "r_votes": 91310,
          "total_votes_cast": 317526,
          "margin_pct": 0.4249,
          "contested": true
        },
        {
          "district": 3,
          "won_by": "D",
          "partisan_lean_d": 0.5423,
          "polsby_popper": 0.1109,
          "d_votes": 126882,
          "r_votes": 107086,
          "total_votes_cast": 233968,
          "margin_pct": 0.0846,
          "contested": true
        },
        {
          "district": 4,
          "won_by": "R",
          "partisan_lean_d": 0.3889,
          "polsby_popper": 0.2925,
          "d_votes": 125885,
          "r_votes": 197803,
          "total_votes_cast": 323688,
          "margin_pct": 0.2222,
          "contested": true
        },
        {
          "district": 5,
          "won_by": "D",
          "partisan_lean_d": 0.7447,
          "polsby_popper": 0.1108,
          "d_votes": 202872,
          "r_votes": 69545,
          "total_votes_cast": 272417,
          "margin_pct": 0.4894,
          "contested": true
        },
        {
          "district": 6,
          "won_by": "D",
          "partisan_lean_d": 0.7505,
          "polsby_popper": 0.2005,
          "d_votes": 160667,
          "r_votes": 53406,
          "total_votes_cast": 214073,
          "margin_pct": 0.501,
          "contested": true
        },
        {
          "district": 7,
          "won_by": "D",
          "partisan_lean_d": 0.5168,
          "polsby_popper": 0.4514,
          "d_votes": 141241,
          "r_votes": 132050,
          "total_votes_cast": 273291,
          "margin_pct": 0.0336,
          "contested": true
        },
        {
          "district": 8,
          "won_by": "R",
          "partisan_lean_d": 0.0,
          "polsby_popper": 0.2804,
          "d_votes": 0,
          "r_votes": 179644,
          "total_votes_cast": 179644,
          "margin_pct": null,
          "contested": false
        },
        {
          "district": 9,
          "won_by": "D",
          "partisan_lean_d": 0.5555,
          "polsby_popper": 0.2527,
          "d_votes": 118373,
          "r_votes": 94704,
          "total_votes_cast": 213077,
          "margin_pct": 0.1111,
          "contested": true
        },
        {
          "district": 10,
          "won_by": "R",
          "partisan_lean_d": 0.4729,
          "polsby_popper": 0.3295,
          "d_votes": 98934,
          "r_votes": 110265,
          "total_votes_cast": 209199,
          "margin_pct": 0.0542,
          "contested": true
        },
        {
          "district": 11,
          "won_by": "D",
          "partisan_lean_d": 0.6973,
          "polsby_popper": 0.1416,
          "d_votes": 200743,
          "r_votes": 87136,
          "total_votes_cast": 287879,
          "margin_pct": 0.3946,
          "contested": true
        },
        {
          "district": 12,
          "won_by": "D",
          "partisan_lean_d": 0.8508,
          "polsby_popper": 0.0535,
          "d_votes": 253709,
          "r_votes": 44478,
          "total_votes_cast": 298187,
          "margin_pct": 0.7017,
          "contested": true
        },
        {
          "district": 13,
          "won_by": "D",
          "partisan_lean_d": 1.0,
          "polsby_popper": 0.0745,
          "d_votes": 250436,
          "r_votes": 0,
          "total_votes_cast": 288582,
          "margin_pct": null,
          "contested": false
        },
        {
          "district": 14,
          "won_by": "D",
          "partisan_lean_d": 0.7892,
          "polsby_popper": 0.0871,
          "d_votes": 203828,
          "r_votes": 54455,
          "total_votes_cast": 258283,
          "margin_pct": 0.5783,
          "contested": true
        },
        {
          "district": 15,
          "won_by": "D",
          "partisan_lean_d": 1.0,
          "polsby_popper": 0.2919,
          "d_votes": 231034,
          "r_votes": 0,
          "total_votes_cast": 231034,
          "margin_pct": null,
          "contested": false
        },
        {
          "district": 16,
          "won_by": "D",
          "partisan_lean_d": 0.5741,
          "polsby_popper": 0.2632,
          "d_votes": 84649,
          "r_votes": 62801,
          "total_votes_cast": 147450,
          "margin_pct": 0.1482,
          "contested": true
        },
        {
          "district": 17,
          "won_by": "D",
          "partisan_lean_d": 0.7354,
          "polsby_popper": 0.1184,
          "d_votes": 159392,
          "r_votes": 57336,
          "total_votes_cast": 216728,
          "margin_pct": 0.4709,
          "contested": true
        },
        {
          "district": 18,
          "won_by": "D",
          "partisan_lean_d": 0.7049,
          "polsby_popper": 0.1867,
          "d_votes": 212831,
          "r_votes": 89103,
          "total_votes_cast": 301934,
          "margin_pct": 0.4098,
          "contested": true
        },
        {
          "district": 19,
          "won_by": "D",
          "partisan_lean_d": 0.7324,
          "polsby_popper": 0.2186,
          "d_votes": 162300,
          "r_votes": 59313,
          "total_votes_cast": 221613,
          "margin_pct": 0.4647,
          "contested": true
        },
        {
          "district": 20,
          "won_by": "D",
          "partisan_lean_d": 0.7407,
          "polsby_popper": 0.2863,
          "d_votes": 172996,
          "r_votes": 60566,
          "total_votes_cast": 233562,
          "margin_pct": 0.4814,
          "contested": true
        },
        {
          "district": 21,
          "won_by": "R",
          "partisan_lean_d": 0.4224,
          "polsby_popper": 0.1925,
          "d_votes": 49119,
          "r_votes": 67164,
          "total_votes_cast": 116283,
          "margin_pct": 0.1552,
          "contested": true
        },
        {
          "district": 22,
          "won_by": "R",
          "partisan_lean_d": 0.3812,
          "polsby_popper": 0.1725,
          "d_votes": 81555,
          "r_votes": 132386,
          "total_votes_cast": 213941,
          "margin_pct": 0.2376,
          "contested": true
        },
        {
          "district": 23,
          "won_by": "R",
          "partisan_lean_d": 0.0,
          "polsby_popper": 0.1974,
          "d_votes": 0,
          "r_votes": 158161,
          "total_votes_cast": 216003,
          "margin_pct": null,
          "contested": false
        },
        {
          "district": 24,
          "won_by": "D",
          "partisan_lean_d": 0.551,
          "polsby_popper": 0.1478,
          "d_votes": 156749,
          "r_votes": 127746,
          "total_votes_cast": 284495,
          "margin_pct": 0.1019,
          "contested": true
        },
        {
          "district": 25,
          "won_by": "R",
          "partisan_lean_d": 0.4522,
          "polsby_popper": 0.2216,
          "d_votes": 106982,
          "r_votes": 129593,
          "total_votes_cast": 236575,
          "margin_pct": 0.0956,
          "contested": true
        },
        {
          "district": 26,
          "won_by": "D",
          "partisan_lean_d": 0.5269,
          "polsby_popper": 0.1705,
          "d_votes": 139072,
          "r_votes": 124863,
          "total_votes_cast": 263935,
          "margin_pct": 0.0538,
          "contested": true
        },
        {
          "district": 27,
          "won_by": "D",
          "partisan_lean_d": 0.6398,
          "polsby_popper": 0.2238,
          "d_votes": 154191,
          "r_votes": 86817,
          "total_votes_cast": 241008,
          "margin_pct": 0.2796,
          "contested": true
        },
        {
          "district": 28,
          "won_by": "D",
          "partisan_lean_d": 0.7649,
          "polsby_popper": 0.17,
          "d_votes": 188703,
          "r_votes": 58008,
          "total_votes_cast": 246711,
          "margin_pct": 0.5297,
          "contested": true
        },
        {
          "district": 29,
          "won_by": "D",
          "partisan_lean_d": 1.0,
          "polsby_popper": 0.2144,
          "d_votes": 111287,
          "r_votes": 0,
          "total_votes_cast": 150281,
          "margin_pct": null,
          "contested": false
        },
        {
          "district": 30,
          "won_by": "D",
          "partisan_lean_d": 1.0,
          "polsby_popper": 0.1946,
          "d_votes": 247851,
          "r_votes": 0,
          "total_votes_cast": 247851,
          "margin_pct": null,
          "contested": false
        },
        {
          "district": 31,
          "won_by": "R",
          "partisan_lean_d": 0.0,
          "polsby_popper": 0.0878,
          "d_votes": 0,
          "r_votes": 161219,
          "total_votes_cast": 161219,
          "margin_pct": null,
          "contested": false
        },
        {
          "district": 32,
          "won_by": "D",
          "partisan_lean_d": 0.657,
          "polsby_popper": 0.125,
          "d_votes": 124903,
          "r_votes": 65208,
          "total_votes_cast": 190111,
          "margin_pct": 0.314,
          "contested": true
        },
        {
          "district": 33,
          "won_by": "D",
          "partisan_lean_d": 1.0,
          "polsby_popper": 0.1027,
          "d_votes": 171860,
          "r_votes": 0,
          "total_votes_cast": 318520,
          "margin_pct": null,
          "contested": false
        },
        {
          "district": 34,
          "won_by": "D",
          "partisan_lean_d": 0.8562,
          "polsby_popper": 0.2686,
          "d_votes": 120367,
          "r_votes": 20223,
          "total_votes_cast": 140590,
          "margin_pct": 0.7123,
          "contested": true
        },
        {
          "district": 35,
          "won_by": "D",
          "partisan_lean_d": 1.0,
          "polsby_popper": 0.2222,
          "d_votes": 142680,
          "r_votes": 0,
          "total_votes_cast": 142680,
          "margin_pct": null,
          "contested": false
        },
        {
          "district": 36,
          "won_by": "D",
          "partisan_lean_d": 0.5294,
          "polsby_popper": 0.3668,
          "d_votes": 110189,
          "r_votes": 97953,
          "total_votes_cast": 208142,
          "margin_pct": 0.0588,
          "contested": true
        },
        {
          "district": 37,
          "won_by": "D",
          "partisan_lean_d": 0.8642,
          "polsby_popper": 0.3273,
          "d_votes": 207039,
          "r_votes": 32541,
          "total_votes_cast": 239580,
          "margin_pct": 0.7283,
          "contested": true
        },
        {
          "district": 38,
          "won_by": "D",
          "partisan_lean_d": 0.6754,
          "polsby_popper": 0.1884,
          "d_votes": 145280,
          "r_votes": 69807,
          "total_votes_cast": 215087,
          "margin_pct": 0.3509,
          "contested": true
        },
        {
          "district": 39,
          "won_by": "R",
          "partisan_lean_d": 0.4221,
          "polsby_popper": 0.2081,
          "d_votes": 106360,
          "r_votes": 145607,
          "total_votes_cast": 251967,
          "margin_pct": 0.1558,
          "contested": true
        },
        {
          "district": 40,
          "won_by": "D",
          "partisan_lean_d": 1.0,
          "polsby_popper": 0.2184,
          "d_votes": 125553,
          "r_votes": 0,
          "total_votes_cast": 125553,
          "margin_pct": null,
          "contested": false
        },
        {
          "district": 41,
          "won_by": "D",
          "partisan_lean_d": 0.5897,
          "polsby_popper": 0.1901,
          "d_votes": 103578,
          "r_votes": 72074,
          "total_votes_cast": 175652,
          "margin_pct": 0.1794,
          "contested": true
        },
        {
          "district": 42,
          "won_by": "R",
          "partisan_lean_d": 0.3941,
          "polsby_popper": 0.1127,
          "d_votes": 84702,
          "r_votes": 130245,
          "total_votes_cast": 214947,
          "margin_pct": 0.2119,
          "contested": true
        },
        {
          "district": 43,
          "won_by": "D",
          "partisan_lean_d": 1.0,
          "polsby_popper": 0.2964,
          "d_votes": 200894,
          "r_votes": 0,
          "total_votes_cast": 200894,
          "margin_pct": null,
          "contested": false
        },
        {
          "district": 44,
          "won_by": "D",
          "partisan_lean_d": 1.0,
          "polsby_popper": 0.0839,
          "d_votes": 165898,
          "r_votes": 0,
          "total_votes_cast": 165898,
          "margin_pct": null,
          "contested": false
        },
        {
          "district": 45,
          "won_by": "R",
          "partisan_lean_d": 0.4154,
          "polsby_popper": 0.3245,
          "d_votes": 121814,
          "r_votes": 171417,
          "total_votes_cast": 293231,
          "margin_pct": 0.1692,
          "contested": true
        },
        {
          "district": 46,
          "won_by": "D",
          "partisan_lean_d": 0.6387,
          "polsby_popper": 0.2744,
          "d_votes": 95694,
          "r_votes": 54121,
          "total_votes_cast": 149815,
          "margin_pct": 0.2775,
          "contested": true
        },
        {
          "district": 47,
          "won_by": "D",
          "partisan_lean_d": 0.5656,
          "polsby_popper": 0.0442,
          "d_votes": 130093,
          "r_votes": 99919,
          "total_votes_cast": 230012,
          "margin_pct": 0.1312,
          "contested": true
        },
        {
          "district": 48,
          "won_by": "R",
          "partisan_lean_d": 0.3902,
          "polsby_popper": 0.1233,
          "d_votes": 113358,
          "r_votes": 177144,
          "total_votes_cast": 290502,
          "margin_pct": 0.2196,
          "contested": true
        },
        {
          "district": 49,
          "won_by": "R",
          "partisan_lean_d": 0.4184,
          "polsby_popper": 0.139,
          "d_votes": 114893,
          "r_votes": 159725,
          "total_votes_cast": 274618,
          "margin_pct": 0.1633,
          "contested": true
        },
        {
          "district": 50,
          "won_by": "R",
          "partisan_lean_d": 0.3231,
          "polsby_popper": 0.2246,
          "d_votes": 83455,
          "r_votes": 174838,
          "total_votes_cast": 258293,
          "margin_pct": 0.3538,
          "contested": true
        },
        {
          "district": 51,
          "won_by": "D",
          "partisan_lean_d": 0.7148,
          "polsby_popper": 0.2381,
          "d_votes": 113934,
          "r_votes": 45464,
          "total_votes_cast": 159398,
          "margin_pct": 0.4296,
          "contested": true
        },
        {
          "district": 52,
          "won_by": "D",
          "partisan_lean_d": 0.5118,
          "polsby_popper": 0.0523,
          "d_votes": 151451,
          "r_votes": 144459,
          "total_votes_cast": 295910,
          "margin_pct": 0.0236,
          "contested": true
        },
        {
          "district": 53,
          "won_by": "D",
          "partisan_lean_d": 0.6143,
          "polsby_popper": 0.1557,
          "d_votes": 164825,
          "r_votes": 103482,
          "total_votes_cast": 268307,
          "margin_pct": 0.2286,
          "contested": true
        }
      ]
    },
    {
      "cycle_year": 2022,
      "congress": 118,
      "total_seats": 52,
      "redistricting_controller": "Independent Commission (CCRC)",
      "notes": "The California Citizens Redistricting Commission drew maps after California lost 1 seat from the 2020 census \u2014 the first loss in state history. The CCRC process involved extensive public hearings; maps produced a delegation roughly proportional to the state's Democratic lean.",
      "efficiency_gap": 0.026,
      "mean_median_diff": 0.0282,
      "seats_d": 40,
      "seats_r": 12,
      "votes_d": 6743737,
      "votes_r": 3859666,
      "seat_vote_ratio_d": 1.2095,
      "avg_compactness": 0.1725,
      "competitiveness": {
        "solid_d": 28,
        "lean_d": 7,
        "competitive": 11,
        "lean_r": 1,
        "solid_r": 5
      },
      "districts": [
        {
          "district": 1,
          "won_by": "R",
          "partisan_lean_d": 0.3793,
          "polsby_popper": 0.2197,
          "d_votes": 93386,
          "r_votes": 152839,
          "total_votes_cast": 246225,
          "margin_pct": 0.2415,
          "contested": true
        },
        {
          "district": 2,
          "won_by": "D",
          "partisan_lean_d": 0.744,
          "polsby_popper": 0.0966,
          "d_votes": 229720,
          "r_votes": 79029,
          "total_votes_cast": 308749,
          "margin_pct": 0.4881,
          "contested": true
        },
        {
          "district": 3,
          "won_by": "R",
          "partisan_lean_d": 0.4635,
          "polsby_popper": 0.1332,
          "d_votes": 156761,
          "r_votes": 181438,
          "total_votes_cast": 338199,
          "margin_pct": 0.073,
          "contested": true
        },
        {
          "district": 4,
          "won_by": "D",
          "partisan_lean_d": 0.678,
          "polsby_popper": 0.1716,
          "d_votes": 176900,
          "r_votes": 84007,
          "total_votes_cast": 260907,
          "margin_pct": 0.356,
          "contested": true
        },
        {
          "district": 5,
          "won_by": "R",
          "partisan_lean_d": 0.3869,
          "polsby_popper": 0.1654,
          "d_votes": 109506,
          "r_votes": 173524,
          "total_votes_cast": 283030,
          "margin_pct": 0.2262,
          "contested": true
        },
        {
          "district": 6,
          "won_by": "D",
          "partisan_lean_d": 0.5595,
          "polsby_popper": 0.3231,
          "d_votes": 121058,
          "r_votes": 95325,
          "total_votes_cast": 216383,
          "margin_pct": 0.1189,
          "contested": true
        },
        {
          "district": 7,
          "won_by": "D",
          "partisan_lean_d": 0.6826,
          "polsby_popper": 0.2462,
          "d_votes": 150618,
          "r_votes": 70033,
          "total_votes_cast": 220651,
          "margin_pct": 0.3652,
          "contested": true
        },
        {
          "district": 8,
          "won_by": "D",
          "partisan_lean_d": 0.7573,
          "polsby_popper": 0.0529,
          "d_votes": 145501,
          "r_votes": 46634,
          "total_votes_cast": 192135,
          "margin_pct": 0.5146,
          "contested": true
        },
        {
          "district": 9,
          "won_by": "D",
          "partisan_lean_d": 0.5482,
          "polsby_popper": 0.2379,
          "d_votes": 95598,
          "r_votes": 78802,
          "total_votes_cast": 174400,
          "margin_pct": 0.0963,
          "contested": true
        },
        {
          "district": 10,
          "won_by": "D",
          "partisan_lean_d": 1.0,
          "polsby_popper": 0.2289,
          "d_votes": 198415,
          "r_votes": 0,
          "total_votes_cast": 251380,
          "margin_pct": null,
          "contested": false
        },
        {
          "district": 11,
          "won_by": "D",
          "partisan_lean_d": 0.8395,
          "polsby_popper": 0.1163,
          "d_votes": 220848,
          "r_votes": 42217,
          "total_votes_cast": 263065,
          "margin_pct": 0.679,
          "contested": true
        },
        {
          "district": 12,
          "won_by": "D",
          "partisan_lean_d": 0.9047,
          "polsby_popper": 0.0853,
          "d_votes": 217110,
          "r_votes": 22859,
          "total_votes_cast": 239969,
          "margin_pct": 0.8095,
          "contested": true
        },
        {
          "district": 13,
          "won_by": "R",
          "partisan_lean_d": 0.4979,
          "polsby_popper": 0.2305,
          "d_votes": 66496,
          "r_votes": 67060,
          "total_votes_cast": 133556,
          "margin_pct": 0.0042,
          "contested": true
        },
        {
          "district": 14,
          "won_by": "D",
          "partisan_lean_d": 0.6934,
          "polsby_popper": 0.3142,
          "d_votes": 137612,
          "r_votes": 60852,
          "total_votes_cast": 198464,
          "margin_pct": 0.3868,
          "contested": true
        },
        {
          "district": 15,
          "won_by": "D",
          "partisan_lean_d": 1.0,
          "polsby_popper": 0.0858,
          "d_votes": 194874,
          "r_votes": 0,
          "total_votes_cast": 194874,
          "margin_pct": null,
          "contested": false
        },
        {
          "district": 16,
          "won_by": "D",
          "partisan_lean_d": 1.0,
          "polsby_popper": 0.1356,
          "d_votes": 241007,
          "r_votes": 0,
          "total_votes_cast": 241007,
          "margin_pct": null,
          "contested": false
        },
        {
          "district": 17,
          "won_by": "D",
          "partisan_lean_d": 0.7093,
          "polsby_popper": 0.2262,
          "d_votes": 127853,
          "r_votes": 52400,
          "total_votes_cast": 180253,
          "margin_pct": 0.4186,
          "contested": true
        },
        {
          "district": 18,
          "won_by": "D",
          "partisan_lean_d": 0.6585,
          "polsby_popper": 0.1714,
          "d_votes": 99776,
          "r_votes": 51737,
          "total_votes_cast": 151513,
          "margin_pct": 0.3171,
          "contested": true
        },
        {
          "district": 19,
          "won_by": "D",
          "partisan_lean_d": 0.6865,
          "polsby_popper": 0.066,
          "d_votes": 194494,
          "r_votes": 88816,
          "total_votes_cast": 283310,
          "margin_pct": 0.373,
          "contested": true
        },
        {
          "district": 20,
          "won_by": "R",
          "partisan_lean_d": 0.3275,
          "polsby_popper": 0.0973,
          "d_votes": 74934,
          "r_votes": 153847,
          "total_votes_cast": 228781,
          "margin_pct": 0.3449,
          "contested": true
        },
        {
          "district": 21,
          "won_by": "D",
          "partisan_lean_d": 0.5418,
          "polsby_popper": 0.1951,
          "d_votes": 68074,
          "r_votes": 57573,
          "total_votes_cast": 125647,
          "margin_pct": 0.0836,
          "contested": true
        },
        {
          "district": 22,
          "won_by": "R",
          "partisan_lean_d": 0.4848,
          "polsby_popper": 0.3108,
          "d_votes": 49862,
          "r_votes": 52994,
          "total_votes_cast": 102856,
          "margin_pct": 0.0305,
          "contested": true
        },
        {
          "district": 23,
          "won_by": "R",
          "partisan_lean_d": 0.3897,
          "polsby_popper": 0.4332,
          "d_votes": 65908,
          "r_votes": 103197,
          "total_votes_cast": 169105,
          "margin_pct": 0.2205,
          "contested": true
        },
        {
          "district": 24,
          "won_by": "D",
          "partisan_lean_d": 0.6057,
          "polsby_popper": 0.114,
          "d_votes": 159019,
          "r_votes": 103533,
          "total_votes_cast": 262552,
          "margin_pct": 0.2113,
          "contested": true
        },
        {
          "district": 25,
          "won_by": "D",
          "partisan_lean_d": 0.5738,
          "polsby_popper": 0.1625,
          "d_votes": 87641,
          "r_votes": 65101,
          "total_votes_cast": 152742,
          "margin_pct": 0.1476,
          "contested": true
        },
        {
          "district": 26,
          "won_by": "D",
          "partisan_lean_d": 0.5453,
          "polsby_popper": 0.2903,
          "d_votes": 134575,
          "r_votes": 112214,
          "total_votes_cast": 246789,
          "margin_pct": 0.0906,
          "contested": true
        },
        {
          "district": 27,
          "won_by": "R",
          "partisan_lean_d": 0.4676,
          "polsby_popper": 0.3643,
          "d_votes": 91892,
          "r_votes": 104624,
          "total_votes_cast": 196516,
          "margin_pct": 0.0648,
          "contested": true
        },
        {
          "district": 28,
          "won_by": "D",
          "partisan_lean_d": 0.6624,
          "polsby_popper": 0.1318,
          "d_votes": 150062,
          "r_votes": 76495,
          "total_votes_cast": 226557,
          "margin_pct": 0.3247,
          "contested": true
        },
        {
          "district": 29,
          "won_by": "D",
          "partisan_lean_d": 1.0,
          "polsby_popper": 0.1766,
          "d_votes": 119435,
          "r_votes": 0,
          "total_votes_cast": 119435,
          "margin_pct": null,
          "contested": false
        },
        {
          "district": 30,
          "won_by": "D",
          "partisan_lean_d": 1.0,
          "polsby_popper": 0.1421,
          "d_votes": 211068,
          "r_votes": 0,
          "total_votes_cast": 211068,
          "margin_pct": null,
          "contested": false
        },
        {
          "district": 31,
          "won_by": "D",
          "partisan_lean_d": 0.5954,
          "polsby_popper": 0.1045,
          "d_votes": 91472,
          "r_votes": 62153,
          "total_votes_cast": 153625,
          "margin_pct": 0.1908,
          "contested": true
        },
        {
          "district": 32,
          "won_by": "D",
          "partisan_lean_d": 0.6917,
          "polsby_popper": 0.1761,
          "d_votes": 167411,
          "r_votes": 74618,
          "total_votes_cast": 242029,
          "margin_pct": 0.3834,
          "contested": true
        },
        {
          "district": 33,
          "won_by": "D",
          "partisan_lean_d": 0.5771,
          "polsby_popper": 0.1863,
          "d_votes": 76588,
          "r_votes": 56119,
          "total_votes_cast": 132707,
          "margin_pct": 0.1542,
          "contested": true
        },
        {
          "district": 34,
          "won_by": "D",
          "partisan_lean_d": 1.0,
          "polsby_popper": 0.2058,
          "d_votes": 121467,
          "r_votes": 0,
          "total_votes_cast": 121467,
          "margin_pct": null,
          "contested": false
        },
        {
          "district": 35,
          "won_by": "D",
          "partisan_lean_d": 0.5736,
          "polsby_popper": 0.2495,
          "d_votes": 75121,
          "r_votes": 55832,
          "total_votes_cast": 130953,
          "margin_pct": 0.1473,
          "contested": true
        },
        {
          "district": 36,
          "won_by": "D",
          "partisan_lean_d": 0.6975,
          "polsby_popper": 0.0897,
          "d_votes": 194299,
          "r_votes": 84264,
          "total_votes_cast": 278563,
          "margin_pct": 0.395,
          "contested": true
        },
        {
          "district": 37,
          "won_by": "D",
          "partisan_lean_d": 1.0,
          "polsby_popper": 0.2953,
          "d_votes": 131880,
          "r_votes": 0,
          "total_votes_cast": 131880,
          "margin_pct": null,
          "contested": false
        },
        {
          "district": 38,
          "won_by": "D",
          "partisan_lean_d": 0.5809,
          "polsby_popper": 0.1383,
          "d_votes": 101260,
          "r_votes": 73051,
          "total_votes_cast": 174311,
          "margin_pct": 0.1618,
          "contested": true
        },
        {
          "district": 39,
          "won_by": "D",
          "partisan_lean_d": 0.5767,
          "polsby_popper": 0.2,
          "d_votes": 75896,
          "r_votes": 55701,
          "total_votes_cast": 131597,
          "margin_pct": 0.1535,
          "contested": true
        },
        {
          "district": 40,
          "won_by": "R",
          "partisan_lean_d": 0.4316,
          "polsby_popper": 0.146,
          "d_votes": 122722,
          "r_votes": 161589,
          "total_votes_cast": 284311,
          "margin_pct": 0.1367,
          "contested": true
        },
        {
          "district": 41,
          "won_by": "R",
          "partisan_lean_d": 0.4765,
          "polsby_popper": 0.0602,
          "d_votes": 112769,
          "r_votes": 123869,
          "total_votes_cast": 236638,
          "margin_pct": 0.0469,
          "contested": true
        },
        {
          "district": 42,
          "won_by": "D",
          "partisan_lean_d": 0.6837,
          "polsby_popper": 0.0405,
          "d_votes": 99217,
          "r_votes": 45903,
          "total_votes_cast": 145120,
          "margin_pct": 0.3674,
          "contested": true
        },
        {
          "district": 43,
          "won_by": "D",
          "partisan_lean_d": 0.7733,
          "polsby_popper": 0.1966,
          "d_votes": 95462,
          "r_votes": 27985,
          "total_votes_cast": 123447,
          "margin_pct": 0.5466,
          "contested": true
        },
        {
          "district": 44,
          "won_by": "D",
          "partisan_lean_d": 0.7221,
          "polsby_popper": 0.0787,
          "d_votes": 100160,
          "r_votes": 38554,
          "total_votes_cast": 138714,
          "margin_pct": 0.4441,
          "contested": true
        },
        {
          "district": 45,
          "won_by": "R",
          "partisan_lean_d": 0.4759,
          "polsby_popper": 0.0794,
          "d_votes": 103466,
          "r_votes": 113960,
          "total_votes_cast": 217426,
          "margin_pct": 0.0483,
          "contested": true
        },
        {
          "district": 46,
          "won_by": "D",
          "partisan_lean_d": 0.6179,
          "polsby_popper": 0.1627,
          "d_votes": 78041,
          "r_votes": 48257,
          "total_votes_cast": 126298,
          "margin_pct": 0.2358,
          "contested": true
        },
        {
          "district": 47,
          "won_by": "D",
          "partisan_lean_d": 0.5172,
          "polsby_popper": 0.1229,
          "d_votes": 137374,
          "r_votes": 128261,
          "total_votes_cast": 265635,
          "margin_pct": 0.0343,
          "contested": true
        },
        {
          "district": 48,
          "won_by": "R",
          "partisan_lean_d": 0.3964,
          "polsby_popper": 0.2017,
          "d_votes": 101900,
          "r_votes": 155171,
          "total_votes_cast": 257071,
          "margin_pct": 0.2072,
          "contested": true
        },
        {
          "district": 49,
          "won_by": "D",
          "partisan_lean_d": 0.5263,
          "polsby_popper": 0.1897,
          "d_votes": 153541,
          "r_votes": 138194,
          "total_votes_cast": 291735,
          "margin_pct": 0.0526,
          "contested": true
        },
        {
          "district": 50,
          "won_by": "D",
          "partisan_lean_d": 0.6284,
          "polsby_popper": 0.044,
          "d_votes": 168816,
          "r_votes": 99819,
          "total_votes_cast": 268635,
          "margin_pct": 0.2568,
          "contested": true
        },
        {
          "district": 51,
          "won_by": "D",
          "partisan_lean_d": 0.6186,
          "polsby_popper": 0.1137,
          "d_votes": 144186,
          "r_votes": 88886,
          "total_votes_cast": 233072,
          "margin_pct": 0.2373,
          "contested": true
        },
        {
          "district": 52,
          "won_by": "D",
          "partisan_lean_d": 0.6667,
          "polsby_popper": 0.1612,
          "d_votes": 100686,
          "r_votes": 50330,
          "total_votes_cast": 151016,
          "margin_pct": 0.3334,
          "contested": true
        }
      ]
    }
  ]
}